innkaupalisti/__init__.py
innkaupalisti/app.py
innkaupalisti/auth.py
innkaupalisti/cli.py
innkaupalisti/list.py
innkaupalisti/login.py
innkaupalisti/store.py
innkaupalisti-0.3.1.dist-info/METADATA
innkaupalisti-0.3.1.dist-info/WHEEL
innkaupalisti-0.3.1.dist-info/RECORD
