Metadata-Version: 2.1
Name: innkaupalisti
Version: 0.3.1
Summary: A shopping list management API
License: MIT
Author: Simon Redding
Author-email: s1m0n.r3dd1ng@gmail.com
Requires-Python: >=3.11,<4.0
Classifier: License :: OSI Approved :: MIT License
Classifier: Programming Language :: Python :: 3
Classifier: Programming Language :: Python :: 3.11
Classifier: Programming Language :: Python :: 3.12
Requires-Dist: Flask (>=3.0.0,<4.0.0)
Requires-Dist: click (>=8.1.7,<9.0.0)
Requires-Dist: flask-restful (>=0.3.10,<0.4.0)
Requires-Dist: flask-sqlalchemy (>=3.1.1,<4.0.0)
Requires-Dist: pyjwt (>=2.8.0,<3.0.0)
